orbin/__init__.py
orbin/cli.py
orbin/database.py
orbin/redis_client.py
orbin/generators/__init__.py
orbin/generators/app_generator.py
orbin/generators/base_generator.py
orbin/generators/controller_generator.py
orbin/generators/model_generator.py
orbin/generators/resource_generator.py
orbin/generators/scaffold_generator.py
orbin/helpers/__init__.py
orbin/helpers/hello_world_helper.py
orbin/templates/app/README.md.j2
orbin/templates/app/alembic.ini.j2
orbin/templates/app/pyproject.toml.j2
orbin/templates/app/requirements.txt.j2
orbin/templates/app/app/__init__.py.j2
orbin/templates/app/app/main.py.j2
orbin/templates/app/app/controllers/__init__.py.j2
orbin/templates/app/app/controllers/base_controller.py.j2
orbin/templates/app/app/models/__init__.py.j2
orbin/templates/app/app/routes/__init__.py.j2
orbin/templates/app/config/__init__.py.j2
orbin/templates/app/config/database.py.j2
orbin/templates/app/config/redis.py.j2
orbin/templates/app/config/settings.py.j2
orbin/templates/app/db/migrations/env.py.j2
orbin/templates/app/db/migrations/script.py.mako
orbin/templates/app/tests/__init__.py.j2
orbin/templates/app/tests/test_main.py.j2
orbin/templates/controller/controller.py.j2
orbin/templates/controller/fixtures.yml.j2
orbin/templates/controller/resource_controller.py.j2
orbin/templates/controller/test_controller.py.j2
orbin/templates/model/migration.py.j2
orbin/templates/model/model.py.j2
orbin/testing/__init__.py
orbin/testing/base_test_case.py
orbin-0.1.0.dist-info/licenses/LICENSE
orbin-0.1.0.dist-info/METADATA
orbin-0.1.0.dist-info/WHEEL
orbin-0.1.0.dist-info/entry_points.txt
orbin-0.1.0.dist-info/top_level.txt
orbin-0.1.0.dist-info/RECORD
