Metadata-Version: 2.4
Name: orbin
Version: 0.1.0
Summary: A powerful framework for building AI-powered chat applications with FastAPI
Author-email: Marcelo Ribeiro <marcelo@floox.ai>
License: MIT
Project-URL: Homepage, https://github.com/marceloribeiro/orbin
Project-URL: Documentation, https://github.com/marceloribeiro/orbin#readme
Project-URL: Repository, https://github.com/marceloribeiro/orbin
Project-URL: Bug Reports, https://github.com/marceloribeiro/orbin/issues
Project-URL: Changelog, https://github.com/marceloribeiro/orbin/blob/main/README.md#changelog
Keywords: fastapi,ai,chat,framework,generators,sqlalchemy,alembic,redis,caching,sessions,convention-over-configuration,crud,restful,orm,migration,scaffold,agent,chatbot,websocket,realtime
Classifier: Development Status :: 4 - Beta
Classifier: Intended Audience :: Developers
Classifier: License :: OSI Approved :: MIT License
Classifier: Operating System :: OS Independent
Classifier: Programming Language :: Python :: 3
Classifier: Programming Language :: Python :: 3.8
Classifier: Programming Language :: Python :: 3.9
Classifier: Programming Language :: Python :: 3.10
Classifier: Programming Language :: Python :: 3.11
Classifier: Programming Language :: Python :: 3.12
Classifier: Framework :: FastAPI
Classifier: Topic :: Internet :: WWW/HTTP :: HTTP Servers
Classifier: Topic :: Software Development :: Libraries :: Application Frameworks
Classifier: Topic :: Software Development :: Code Generators
Classifier: Topic :: Communications :: Chat
Classifier: Topic :: Scientific/Engineering :: Artificial Intelligence
Classifier: Topic :: Database
Requires-Python: >=3.8
License-File: LICENSE
Requires-Dist: fastapi>=0.104.1
Requires-Dist: uvicorn[standard]>=0.24.0
Requires-Dist: sqlalchemy>=2.0.23
Requires-Dist: alembic>=1.12.1
Requires-Dist: psycopg2-binary>=2.9.9
Requires-Dist: python-dotenv>=1.0.0
Requires-Dist: ipython>=8.0.0
Requires-Dist: jinja2>=3.0.0
Requires-Dist: inflect>=7.0.0
Requires-Dist: redis>=5.0.0
Provides-Extra: dev
Requires-Dist: pytest>=6.0; extra == "dev"
Requires-Dist: pytest-cov>=2.0; extra == "dev"
Requires-Dist: black>=21.0; extra == "dev"
Requires-Dist: flake8>=3.8; extra == "dev"
Requires-Dist: mypy>=0.800; extra == "dev"
Dynamic: license-file
